CalculatorAugustas/__init__.py
CalculatorAugustas/_version.py
CalculatorAugustas/calculator.py
calculatoraugustas-1.0.0.dist-info/LICENSE
calculatoraugustas-1.0.0.dist-info/WHEEL
calculatoraugustas-1.0.0.dist-info/METADATA
calculatoraugustas-1.0.0.dist-info/RECORD
