Metadata-Version: 2.1
Name: CalculatorAugustas
Version: 1.0.0
Summary: Calculator with its own built-in memory. Let's do some quick maths!
Author: Augustas Bliujus
Classifier: License :: OSI Approved :: MIT License
